{
  "happy": {
    "validations": [
      "You're in a good place right now, enjoy it!",
      "That's a nice mood to be in – hold onto it!",
      "Love that you're feeling upbeat.",
      "Sounds like today is treating you well!",
      "You've earned this good feeling!",
      "It's nice when the day flows smoothly!",
      "Moments like this matter more than you think.",
      "A little happiness goes a long way!",
      "Nice – savour that good vibe!",
      "Keep riding that positive wave!",
      "Your energy is contagious right now!",
      "This is what it's all about!",
      "You deserve to feel this good.",
      "Happiness looks good on you!",
      "What a wonderful place to be."
    ],
    "microActions": {
      "daytime": [
        "Text one person to spread the happiness!",
        "Write down one thing that went well today.",
        "Take a quick photo of something making you smile!",
        "Put on a song you love for 2 minutes.",
        "Share a kind message with someone!",
        "Drink a glass of water to keep the energy up.",
        "Take a short walk to enjoy the mood!",
        "Do one small task you've been avoiding.",
        "Smile at someone nearby!",
        "Plan one nice thing for later.",
        "Share your positive energy with a friend.",
        "Do something creative for 5 minutes.",
        "Help brighten someone else's day.",
        "Try something you've been curious about.",
        "Take a moment to appreciate this feeling."
      ],
      "evening": [
        "Write down what made you happy today.",
        "Share your good mood with someone.",
        "Do something kind for yourself.",
        "Plan to do more of what makes you happy.",
        "Celebrate this feeling - you earned it!",
        "Text a friend something positive.",
        "Listen to your favorite uplifting song.",
        "Reflect on why today felt good.",
        "Set an intention for tomorrow.",
        "Treat yourself to something small.",
        "Journal about this positive moment.",
        "Plan a fun activity for the weekend.",
        "Call someone you care about.",
        "Watch something that makes you laugh.",
        "Wind down with gratitude."
      ]
    }
  },
  "stressed": {
    "validations": [
      "It makes sense you feel stretched right now.",
      "You've got a lot on your plate – that's not easy.",
      "Feeling stressed doesn't mean you're failing!",
      "Anyone in your shoes would feel the pressure.",
      "This moment is heavy, but it will pass.",
      "You don't have to solve everything at once!",
      "It's okay to feel overwhelmed sometimes.",
      "Stress usually means you care!",
      "You're doing more than you realise.",
      "Take it one step at a time!",
      "You're allowed to slow down for a minute.",
      "Breathe – you're still in control.",
      "This feeling is temporary, not permanent.",
      "You're handling more than most people could.",
      "It's okay to ask for help when you need it."
    ],
    "microActions": {
      "daytime": [
        "Do 5 slow breaths: in for 4 seconds, out for 6 seconds.",
        "Stand up and shake out your shoulders!",
        "Drink a few sips of water.",
        "Close your eyes for 30 seconds.",
        "Stretch your neck around gently.",
        "Put your phone face-down for 5 minutes.",
        "Take a quick walk and back.",
        "Break one task you're working on into two easier steps.",
        "Play a calm song quietly.",
        "Answer the question: 'What actually matters right now?'",
        "Write down the one thing you can control.",
        "Step outside for 2 minutes of fresh air.",
        "Do a quick body scan - notice where you're tense.",
        "Message a friend something lighthearted.",
        "Give yourself permission to take a break."
      ],
      "evening": [
        "Take 6 deep breaths before doing anything else.",
        "Dim the lights and sit quietly for 2 minutes.",
        "Write down 3 things you accomplished today.",
        "Listen to a calming playlist.",
        "Stretch your body gently for 5 minutes.",
        "Put away all screens for 15 minutes.",
        "Make a to-do list for tomorrow to clear your mind.",
        "Have a warm drink slowly.",
        "Close your eyes and picture a peaceful place.",
        "Acknowledge that you made it through the day.",
        "Do something that feels comforting.",
        "Talk to someone you trust about how you feel.",
        "Watch something calming or funny.",
        "Prepare for a restful night's sleep.",
        "Remind yourself: tomorrow is a new day."
      ]
    }
  },
  "lonely": {
    "validations": [
      "Even surrounded by people, loneliness can sneak in.",
      "Wanting connection is completely human.",
      "This feeling says nothing bad about you.",
      "You don't have to handle it alone.",
      "Being lonely doesn't mean you're unlikeable.",
      "You deserve to feel included.",
      "Connection often starts with one tiny step.",
      "This feeling is real, but it can shift.",
      "You matter more than you think!",
      "Loneliness is tough, but it's temporary.",
      "You're not invisible – people care about you.",
      "Reaching out is brave, not weak.",
      "Sometimes we all need to feel seen.",
      "You're worthy of connection and companionship.",
      "This feeling won't last forever."
    ],
    "microActions": {
      "daytime": [
        "Send a simple 'hey, how are you?' to one person.",
        "Smile or say hi to one classmate.",
        "Plan one meet-up with someone you like.",
        "Write a short message to future-you.",
        "Look through old photos that feel warm.",
        "Ask someone a simple question.",
        "Follow up with someone you miss.",
        "Join a group chat or activity.",
        "Reach out to a family member.",
        "Compliment someone genuinely.",
        "Text someone you haven't talked to in a while.",
        "Sit near people instead of alone.",
        "Share something you're interested in online.",
        "Attend a club or group activity.",
        "Be kind to yourself – you're doing your best."
      ],
      "evening": [
        "Text someone 'I was thinking about you.'",
        "Write down names of people who care about you.",
        "Call or video chat with a friend or family member.",
        "Join an online community around your interests.",
        "Plan to see someone this week.",
        "Reflect on a good memory with a friend.",
        "Reach out to someone and be honest about feeling lonely.",
        "Watch or listen to something comforting.",
        "Remind yourself of past connections that felt good.",
        "Do something kind for yourself.",
        "Journal about what kind of connection you're craving.",
        "Set an intention to reach out tomorrow.",
        "Remember that many people feel this way too.",
        "Practice self-compassion – loneliness is hard.",
        "Give yourself credit for acknowledging this feeling."
      ]
    }
  },
  "excited": {
    "validations": [
      "Excitement means something matters to you!",
      "That spark is worth enjoying!",
      "It's nice to feel fired up about something!",
      "Big or small – excitement is powerful!",
      "Let yourself enjoy this feeling!",
      "Looks like motivation found you today!",
      "Channel that energy into something fun!",
      "You seem ready to take on the day!",
      "Your enthusiasm is inspiring!",
      "This energy can fuel great things!",
      "Ride this wave as far as it takes you!",
      "Excitement like this doesn't come every day!",
      "You're buzzing with possibility!",
      "This is the feeling that makes things happen!",
      "Keep that fire burning!"
    ],
    "microActions": {
      "daytime": [
        "Write down what you're excited about.",
        "Take 5 minutes to plan your next step!",
        "Share your excitement with a friend!",
        "Put on an upbeat song!",
        "Take a photo with someone to remember the moment!",
        "Channel this energy into a project you care about.",
        "Do something productive while you have the energy!",
        "Tell someone what's got you pumped.",
        "Make a quick list of what you want to accomplish.",
        "Use this momentum to tackle something challenging.",
        "Celebrate what's making you feel this way!",
        "Text someone your good news.",
        "Do a little victory dance (seriously!).",
        "Capture this feeling in your journal.",
        "Let yourself dream big right now."
      ],
      "evening": [
        "Reflect on what's fueling your excitement.",
        "Plan your next move for tomorrow.",
        "Share your enthusiasm with someone close.",
        "Write down your goals while you're motivated.",
        "Channel this energy into something creative.",
        "Celebrate what got you to this point.",
        "Make a vision board or list of aspirations.",
        "Watch or read something inspiring.",
        "Set an early alarm to keep the momentum going.",
        "Journal about what this feeling means to you.",
        "Tell someone about your plans.",
        "Do some light prep for tomorrow's tasks.",
        "Wind down while still feeling positive.",
        "Fall asleep thinking about possibilities.",
        "Enjoy this feeling – you've earned it!"
      ]
    }
  },
  "frustrated": {
    "validations": [
      "It's okay to feel irritated right now.",
      "Things not working out can be draining.",
      "Frustration usually means you care.",
      "This moment is tough – not you.",
      "Take a breath; you don't have to react immediately.",
      "You've hit a wall, not the end.",
      "This feeling doesn't define your day!",
      "Step back – you don't need to fight it.",
      "It's okay to pause and reset.",
      "Frustration passes, even if slowly.",
      "You're allowed to feel annoyed sometimes.",
      "Not everything goes the way we want – and that's okay.",
      "This setback is temporary, not permanent.",
      "You're not broken – the situation is just hard.",
      "Give yourself grace in this moment."
    ],
    "microActions": {
      "daytime": [
        "Unclench your jaw and drop your shoulders.",
        "Take 6 slow breaths before doing anything.",
        "Stand up and walk for 60 seconds.",
        "Write one sentence about what's bothering you, and reflect.",
        "Get a quick sip of water!",
        "Count backwards from 20.",
        "Step outside for fresh air!",
        "Ask for help instead of pushing alone!",
        "Listen to a song to reset your mood!",
        "Take a 5-minute break from whatever's frustrating you.",
        "Talk to someone about what's going wrong.",
        "Stretch your body to release tension.",
        "Acknowledge the frustration, then let it go.",
        "Focus on one small thing you CAN control.",
        "Remind yourself: this too shall pass."
      ],
      "evening": [
        "Write down what frustrated you – then close the book.",
        "Do something calming to shift your mood.",
        "Take a warm shower to wash off the day.",
        "Listen to calming music or nature sounds.",
        "Practice deep breathing for 5 minutes.",
        "Watch something lighthearted or funny.",
        "Talk it out with someone you trust.",
        "Reflect on what you learned from the frustration.",
        "Give yourself permission to let it go for tonight.",
        "Do something that makes you feel in control.",
        "Journal about what you'll do differently tomorrow.",
        "Stretch or do gentle movement.",
        "Remind yourself of what went RIGHT today.",
        "Plan a fresh start for tomorrow.",
        "Be kind to yourself – today was hard."
      ]
    }
  }
}